two_tables/updater.py
two_tables-0.1.2.dist-info/entry_points.txt
two_tables-0.1.2.dist-info/WHEEL
two_tables-0.1.2.dist-info/METADATA
two_tables-0.1.2.dist-info/RECORD
