Metadata-Version: 2.1
Name: two-tables
Version: 0.1.2
Summary: Automatically update two tables
License: GPL-3.0-or-later
Author: LilyWhite
Author-email: lilywhite2005@outlook.com
Requires-Python: >=3.7,<4.0
Classifier: License :: OSI Approved :: GNU General Public License v3 or later (GPLv3+)
Classifier: Programming Language :: Python :: 3
Classifier: Programming Language :: Python :: 3.10
Classifier: Programming Language :: Python :: 3.7
Classifier: Programming Language :: Python :: 3.8
Classifier: Programming Language :: Python :: 3.9
Requires-Dist: docopt (>=0.6.2,<0.7.0)
Requires-Dist: openpyxl (>=3.0.10,<4.0.0)
